{
  "$schema": "https://json-schema.org/draft/2020-12/schema",
  "type": "object",
  "additionalProperties": false,
  "patternProperties": {
    "^([a-z0-9-]+|\/)$": {
      "type": "object",
      "additionalProperties": false,
      "properties": {
        "title": {
          "type": "string",
          "description": "Leading text of the <title> tag in the document <head>. If not provided, will default to heading."
        },
        "titleTrailer": {
          "type": "string",
          "description": "Trailing text of the <title> tag in the document <head>",
          "default": "Nicolaos Skimas"
        },
        "description": {
          "type": "string",
          "description": "The content of the <meta> description tag in the document <head>",
          "maxLength": 150
        },
        "heading": {
          "type": "string",
          "description": "Top level page heading shown in the page header. Used for leading text of the <title> tag if title is not specified."
        },
        "subHeading": {
          "type": "string",
          "description": "Supporting text in the page header under the heading"
        },
        "publishDate": {
          "type": "string",
          "format": "date"
        },
        "template": {
          "type": "string",
          "description": "A page layout that can be used referenced by blocks",
          "enum": ["no-content", "thought"]
        }
      },
      "required": ["heading"],
      "if": {
        "properties": {
          "template": { "const": "thought" }
        },
        "required": ["template"]
      },
      "then": { "required": ["publishDate", "description"] }
    }
  }
}
